{
    "raw_dir": "./dataset/raw",
    "processed_dir": "./dataset/processed",
    "max_cutoff_distance": 5.0,
    "chunk_size": 1000,
    "num_chunks": null,
    "trainset_ratio": 0.6,
    "testset_ratio": 0.2,
    "valset_ratio": 0.2,
    "split_dataset_seed": 1024,
    "batch_size": 512,
    "data_loader_shuffle": true,
    "data_loader_seed": 1024,
    "num_workers": 0,
    "conv_out_dim": 200,
    "num_layers": 2,
    "num_pre_fc": 5,
    "pre_fc_dim": 100,
    "num_post_fc": 5,
    "post_fc_dim": 100,
    "dropout_rate": 0.4,
    "epochs": 1000,
    "learning_rate": 0.01,
    "data_min": null,
    "data_max": null
}